cicinlang/.DS_Store
cicinlang/__init__.py
cicinlang/cicinlang.py
cicinlang/entry.py
cicinlang/errors.py
cicinlang/interpreter.py
cicinlang/lexer.py
cicinlang/nodes.py
cicinlang/parser_.py
cicinlang/utils.py
cicinlang-0.1.2.dist-info/LICENSE
cicinlang-0.1.2.dist-info/METADATA
cicinlang-0.1.2.dist-info/WHEEL
cicinlang-0.1.2.dist-info/entry_points.txt
cicinlang-0.1.2.dist-info/RECORD
