Metadata-Version: 2.1
Name: cicinlang
Version: 0.1.2
Summary: A general purpose, procedural, interpreted programming language made using Python
Author: Farhan Tajwar Romit
Author-email: tajwarfarhan48@gmail.com
Requires-Python: >=3.7,<4.0
Classifier: Programming Language :: Python :: 3
Classifier: Programming Language :: Python :: 3.7
Classifier: Programming Language :: Python :: 3.8
Classifier: Programming Language :: Python :: 3.9
Classifier: Programming Language :: Python :: 3.10
Classifier: Programming Language :: Python :: 3.11
